mlxim/__init__.py
mlxim/callbacks/__init__.py
mlxim/callbacks/checkpoint.py
mlxim/data/__init__.py
mlxim/data/_base.py
mlxim/data/_utils.py
mlxim/data/folder.py
mlxim/data/loader.py
mlxim/io/__init__.py
mlxim/io/config.py
mlxim/io/image.py
mlxim/metrics/__init__.py
mlxim/metrics/classification.py
mlxim/model/__init__.py
mlxim/model/_config.py
mlxim/model/_factory.py
mlxim/model/_registry.py
mlxim/model/_utils.py
mlxim/model/layers/__init__.py
mlxim/model/layers/_ops.py
mlxim/model/layers/functional.py
mlxim/model/layers/misc.py
mlxim/model/layers/mlp.py
mlxim/model/layers/pool.py
mlxim/model/layers/utils.py
mlxim/model/layers/weight_init.py
mlxim/model/mobilenet/__init__.py
mlxim/model/mobilenet/_factory.py
mlxim/model/mobilenet/mobilenet.py
mlxim/model/regnet/__init__.py
mlxim/model/regnet/_factory.py
mlxim/model/regnet/regnet.py
mlxim/model/resnet/__init__.py
mlxim/model/resnet/_factory.py
mlxim/model/resnet/resnet.py
mlxim/model/swin_transformer/__init__.py
mlxim/model/swin_transformer/_factory.py
mlxim/model/swin_transformer/swin_transformer.py
mlxim/model/vit/__init__.py
mlxim/model/vit/_factory.py
mlxim/model/vit/vit.py
mlxim/trainer/__init__.py
mlxim/trainer/trainer.py
mlxim/transform/__init__.py
mlxim/transform/_utils.py
mlxim/transform/imagenet.py
mlxim/utils/__init__.py
mlxim/utils/imagenet.py
mlxim/utils/time.py
mlxim/utils/validation.py
mlx_image-0.1.8.dist-info/LICENSE
mlx_image-0.1.8.dist-info/METADATA
mlx_image-0.1.8.dist-info/WHEEL
mlx_image-0.1.8.dist-info/RECORD
