Metadata-Version: 2.1
Name: mlx-image
Version: 0.1.8
Summary: Apple MLX image models library
Author: Riccardo Musmeci
Author-email: riccardomusmeci92@gmail.com
Requires-Python: >=3.10,<4.0
Classifier: Programming Language :: Python :: 3
Classifier: Programming Language :: Python :: 3.10
Classifier: Programming Language :: Python :: 3.11
Classifier: Programming Language :: Python :: 3.12
Classifier: Programming Language :: Python :: 3.13
Provides-Extra: dev
Provides-Extra: test
Requires-Dist: Pillow (==10.2.0)
Requires-Dist: albumentations (==1.4.1)
Requires-Dist: black[jupyter] (==23.3.0) ; extra == "dev"
Requires-Dist: docstr-coverage (==2.2.0) ; extra == "dev"
Requires-Dist: huggingface_hub (==0.21.4)
Requires-Dist: matplotlib
Requires-Dist: mlx (==0.21.0)
Requires-Dist: mypy (==1.2.0) ; extra == "dev"
Requires-Dist: numpy (==1.26.2)
Requires-Dist: opencv-python (==4.9.0.80)
Requires-Dist: pandas (==2.2.1)
Requires-Dist: pre-commit (==3.3.1) ; extra == "dev"
Requires-Dist: pytest (==7.3.1) ; extra == "test"
Requires-Dist: pytest-cov (==4.0.0) ; extra == "test"
Requires-Dist: pytest-sugar (==0.9.7) ; extra == "test"
Requires-Dist: pytest-xdist (==3.2.1) ; extra == "test"
Requires-Dist: ruff (==0.0.264) ; extra == "dev"
Requires-Dist: safetensors (==0.4.2)
Requires-Dist: torch (==2.0.0) ; extra == "dev"
Requires-Dist: torchvision (==0.17.1) ; extra == "dev"
Requires-Dist: tqdm
Requires-Dist: twine (>=4.0.0,<5) ; extra == "dev"
Requires-Dist: types-pyyaml (>=6.0.12.12,<7.0.0.0)
